srx_lib_llm/__init__.py
srx_lib_llm/batch.py
srx_lib_llm/batch_state.py
srx_lib_llm/cache.py
srx_lib_llm/chat.py
srx_lib_llm/config_utils.py
srx_lib_llm/fastapi.py
srx_lib_llm/instrumentation.py
srx_lib_llm/mapping.py
srx_lib_llm/models.py
srx_lib_llm/openai_compat.py
srx_lib_llm/request_validation.py
srx_lib_llm/schema_validation.py
srx_lib_llm/schemas.py
srx_lib_llm/storage.py
srx_lib_llm/structured.py
srx_lib_llm/webhooks.py
srx_lib_llm/tools/__init__.py
srx_lib_llm/tools/base.py
srx_lib_llm/tools/tavily.py
srx_lib_llm-1.14.0.dist-info/METADATA
srx_lib_llm-1.14.0.dist-info/WHEEL
srx_lib_llm-1.14.0.dist-info/RECORD
