Metadata-Version: 2.1
Name: srx-lib-llm
Version: 1.14.0
Summary: LLM helpers for SRX services: ChatOpenAI wrapper, tool base, Tavily tool, OpenAI Batch API, and infrastructure-agnostic batch state management
Author-email: SRX <dev@srx.id>
Requires-Python: >=3.12
Requires-Dist: httpx<1,>=0.27.0
Requires-Dist: langchain-community>=0.4.1
Requires-Dist: langchain-core>=1.0.5
Requires-Dist: langchain-openai>=1.0.3
Requires-Dist: langchain>=1.0.7
Requires-Dist: langfuse<4,>=3.8.0
Requires-Dist: langgraph>=1.0.3
Requires-Dist: openai<3,>=2.6.1
Requires-Dist: tavily-python<0.8,>=0.7.13
Provides-Extra: dev
Requires-Dist: pytest-asyncio<1,>=0.23.0; extra == 'dev'
Requires-Dist: pytest<9,>=8.0.0; extra == 'dev'
